metaflow_extensions/torchrun/plugins/mfextinit_torchrun.py
metaflow_extensions/torchrun/plugins/torchrun_libs/__init__.py
metaflow_extensions/torchrun/plugins/torchrun_libs/constants.py
metaflow_extensions/torchrun/plugins/torchrun_libs/datastore.py
metaflow_extensions/torchrun/plugins/torchrun_libs/exceptions.py
metaflow_extensions/torchrun/plugins/torchrun_libs/executor.py
metaflow_extensions/torchrun/plugins/torchrun_libs/status_notifier.py
metaflow_extensions/torchrun/plugins/torchrun_libs/torch_distributed_setup.py
metaflow_extensions/torchrun/plugins/torchrun_libs/torchrun_decorator.py
metaflow_extensions/torchrun/toplevel/__init__.py
metaflow_extensions/torchrun/toplevel/toplevel.py
metaflow_torchrun-0.1.2.dist-info/METADATA
metaflow_torchrun-0.1.2.dist-info/WHEEL
metaflow_torchrun-0.1.2.dist-info/top_level.txt
metaflow_torchrun-0.1.2.dist-info/RECORD
