Metadata-Version: 2.1
Name: metaflow-torchrun
Version: 0.1.2
Summary: A torchrun decorator for Metaflow
Author: Outerbounds
Author-email: hello@outerbounds.com
